apollo_proxy/__init__.py
apollo_proxy/client.py
apollo_proxy/helper.py
apollo_proxy/logger_handler.py
apollo_proxy/python_2x.py
apollo_proxy/python_3x.py
python_apollo_proxy-0.1.8.dist-info/LICENSE
python_apollo_proxy-0.1.8.dist-info/METADATA
python_apollo_proxy-0.1.8.dist-info/WHEEL
python_apollo_proxy-0.1.8.dist-info/top_level.txt
python_apollo_proxy-0.1.8.dist-info/RECORD
