Metadata-Version: 2.1
Name: python-apollo-proxy
Version: 0.1.8
Summary: This is my apollo proxy client package
Home-page: https://github.com/ckf10000/python-apollo
Author: ckf10000
Author-email: ckf10000@sina.com
Classifier: Programming Language :: Python :: 3
Classifier: License :: OSI Approved :: MIT License
Classifier: Operating System :: OS Independent
License-File: LICENSE
